wirednand/__init__.py
wirednand/__main__.py
wirednand/core.py
wirednand-0.1.0.dist-info/entry_points.txt
wirednand-0.1.0.dist-info/LICENSE
wirednand-0.1.0.dist-info/WHEEL
wirednand-0.1.0.dist-info/METADATA
wirednand-0.1.0.dist-info/RECORD
