Metadata-Version: 2.1
Name: wirednand
Version: 0.1.0
Summary: Logic circuit simulator. Building a computer from NAND gates.
Home-page: https://github.com/guiferviz/wirednand
License: MIT
Keywords: wirednand
Author: guiferviz
Author-email: guiferviz@gmail.com
Requires-Python: >=3.10,<4.0
Classifier: License :: OSI Approved :: MIT License
Classifier: Natural Language :: English
Classifier: Programming Language :: Python
Classifier: Programming Language :: Python :: 3
Classifier: Programming Language :: Python :: 3.10
Classifier: Programming Language :: Python :: 3
Classifier: Topic :: Software Development
Project-URL: Bug Tracker, https://github.com/guiferviz/wirednand/issues
Project-URL: Documentation, https://guiferviz.github.io/wirednand
Project-URL: Repository, https://github.com/guiferviz/wirednand
Project-URL: Source, https://github.com/guiferviz/wirednand
